opengrid/__about__.py
opengrid/__init__.py
opengrid/datasets/__init__.py
opengrid/datasets/datasets.py
opengrid/datasets/elec_power_min_1sensor.pkl
opengrid/datasets/electricity_2016_hour.pkl
opengrid/datasets/gas_2016_hour.pkl
opengrid/datasets/gas_dec2016_min.pkl
opengrid/datasets/water_2016_hour.pkl
opengrid/datasets/water_march2015_min.pkl
opengrid/datasets/weather_2016_hour.pkl
opengrid/library/__init__.py
opengrid/library/analysis.py
opengrid/library/exceptions.py
opengrid/library/plotting.py
opengrid/library/regression.py
opengrid/library/utils.py
opengrid/library/weather.py
opengrid/recipes/__init__.py
opengrid/tests/__init__.py
opengrid/tests/test_analyses.py
opengrid/tests/test_plotting.py
opengrid/tests/test_regression.py
opengrid/tests/test_utils.py
opengrid/tests/test_weather.py
opengrid-0.5.10.data/data/LICENSE
opengrid-0.5.10.data/data/README.md
opengrid-0.5.10.data/data/requirements.txt
opengrid-0.5.10.dist-info/METADATA
opengrid-0.5.10.dist-info/RECORD
opengrid-0.5.10.dist-info/WHEEL
opengrid-0.5.10.dist-info/top_level.txt
