Metadata-Version: 2.1
Name: opengrid
Version: 0.5.10
Summary: Open-source algorithms for data-driven building analysis and control
Home-page: https://opengridcc.github.io
Author: Roel De Coninck and many others
Author-email: roeldeconinck@gmail.com
License: Apache 2.0
Keywords: algorithms buildings monitoring analysis control
Platform: UNKNOWN
Classifier: Development Status :: 3 - Alpha
Classifier: Intended Audience :: Developers
Classifier: Topic :: Scientific/Engineering
Classifier: License :: OSI Approved :: Apache Software License
Classifier: Programming Language :: Python :: 3
Classifier: Programming Language :: Python :: 3.3
Classifier: Programming Language :: Python :: 3.4
Classifier: Programming Language :: Python :: 3.5
Classifier: Programming Language :: Python :: 3.6
